tortoolkit/__init__.py
tortoolkit/__main__.py
tortoolkit/ttk_client.py
tortoolkit/config/DefaultCommands.py
tortoolkit/config/ExecVarsSample.py
tortoolkit/config/__init__.py
tortoolkit/core/HandleManager.py
tortoolkit/core/__init__.py
tortoolkit/core/base_task.py
tortoolkit/core/getCommand.py
tortoolkit/core/getVars.py
tortoolkit/core/settings.py
tortoolkit/core/task_sequencer.py
tortoolkit/core/user_settings.py
tortoolkit/core/varholdern.py
tortoolkit/database/__init__.py
tortoolkit/database/abstract_db.py
tortoolkit/database/dbhandler.py
tortoolkit/database/mongo_db.py
tortoolkit/database/mongo_impl.py
tortoolkit/database/postgres_impl.py
tortoolkit/database/postrgres_db.py
tortoolkit/database/upload_db.py
tortoolkit/downloaders/__init__.py
tortoolkit/downloaders/aria2_downloader.py
tortoolkit/downloaders/direct_link_gen.py
tortoolkit/downloaders/mega_downloader.py
tortoolkit/downloaders/pytdl_downloader.py
tortoolkit/downloaders/qbittorrent_downloader.py
tortoolkit/downloaders/ytdl_downloader.py
tortoolkit/downloaders/ytdl_downloader_new.py
tortoolkit/server/__init__.py
tortoolkit/server/nodes.py
tortoolkit/server/server.py
tortoolkit/server/static/__init__.py
tortoolkit/server/templates/__init__.py
tortoolkit/status/__init__.py
tortoolkit/status/aria2_status.py
tortoolkit/status/base_status.py
tortoolkit/status/mega_status.py
tortoolkit/status/qbittorrent_status.py
tortoolkit/status/rclone_status.py
tortoolkit/status/status_manager.py
tortoolkit/status/tg_upload_status.py
tortoolkit/status/ytdl_status.py
tortoolkit/uploaders/Ftele.py
tortoolkit/uploaders/__init__.py
tortoolkit/uploaders/archiver.py
tortoolkit/uploaders/extractor.py
tortoolkit/uploaders/rclone_uploader.py
tortoolkit/uploaders/telegram_uploader.py
tortoolkit/utils/__init__.py
tortoolkit/utils/admin_check.py
tortoolkit/utils/hash_utils.py
tortoolkit/utils/human_format.py
tortoolkit/utils/misc_utils.py
tortoolkit/utils/size.py
tortoolkit/utils/speedtest.py
tortoolkit/utils/video_helpers.py
tortk_example-0.0.3.dist-info/LICENSE
tortk_example-0.0.3.dist-info/METADATA
tortk_example-0.0.3.dist-info/WHEEL
tortk_example-0.0.3.dist-info/top_level.txt
tortk_example-0.0.3.dist-info/RECORD
